charts/mcp-server/Chart.yaml
charts/mcp-server/values.yaml
charts/mcp-server/templates/_helpers.tpl
charts/mcp-server/templates/configmap.yaml
charts/mcp-server/templates/deployment.yaml
charts/mcp-server/templates/service.yaml
charts/mcp-server/templates/serviceaccount.yaml
docs/custom_templates.md
docs/faq.md
docs/filesystem-server-usage.md
docs/index.md
docs/kubernetes.md
docs/stdio-tool-execution.md
docs/tool-discovery.md
docs/cli/cleanup.md
docs/cli/config.md
docs/cli/connect.md
docs/cli/create.md
docs/cli/deploy.md
docs/cli/discover-tools.md
docs/cli/index.md
docs/cli/interactive-cli.doc
docs/cli/interactive.md
docs/cli/list.md
docs/cli/logs.md
docs/cli/run-tool.md
docs/cli/run.md
docs/cli/shell.md
docs/cli/stop.md
docs/cli/tools.md
docs/client/examples.md
docs/client/index.md
docs/client/servers.md
docs/client/templates.md
docs/client/tools.md
docs/configuration/environment-variables.md
docs/development/architecture.md
docs/development/setup.md
docs/getting-started/configuration.md
docs/getting-started/first-deployment.md
docs/getting-started/installation.md
docs/getting-started/quickstart.md
docs/guides/contributing.md
docs/guides/creating-templates.md
docs/guides/deployment.md
docs/guides/testing.md
docs/guides/troubleshooting.md
docs/guides/usage.md
docs/interactive-cli/call.md
docs/interactive-cli/cleanup.md
docs/interactive-cli/clear_config.md
docs/interactive-cli/commands.md
docs/interactive-cli/configure.md
docs/interactive-cli/deploy.md
docs/interactive-cli/help.md
docs/interactive-cli/logs.md
docs/interactive-cli/quit.md
docs/interactive-cli/remove.md
docs/interactive-cli/select.md
docs/interactive-cli/servers.md
docs/interactive-cli/show_config.md
docs/interactive-cli/status.md
docs/interactive-cli/stop.md
docs/interactive-cli/templates.md
docs/interactive-cli/tools.md
docs/interactive-cli/unselect.md
docs/server-templates/index.md
docs/stylesheets/extra.css
docs/templates/creating.md
docs/templates/development.md
docs/templates/file-server.md
mcp_platform-1.3.1.dist-info/licenses/LICENSE
mcp_platform-1.3.1.dist-info/licenses/NOTICE
mcp_platform-1.3.1.dist-info/METADATA
mcp_platform-1.3.1.dist-info/WHEEL
mcp_platform-1.3.1.dist-info/entry_points.txt
mcp_platform-1.3.1.dist-info/top_level.txt
mcp_platform-1.3.1.dist-info/RECORD
